patchpanel/__init__.py
patchpanel/connectivity.py
patchpanel/matrix.py
patchpanel/problem.py
patchpanel-0.1.data/data/LICENSE
patchpanel-0.1.dist-info/LICENSE
patchpanel-0.1.dist-info/METADATA
patchpanel-0.1.dist-info/WHEEL
patchpanel-0.1.dist-info/top_level.txt
patchpanel-0.1.dist-info/RECORD
