Metadata-Version: 2.1
Name: patchpanel
Version: 0.1
Summary: Solves constrained connectivity between sources & sinks
Home-page: https://github.com/Intuity
Author: Peter Birch
License: Apache License, Version 2.0
Project-URL: Source, https://github.com/Intuity/patchpanel
Platform: UNKNOWN
